cell_machine_levels/V1.py
cell_machine_levels/V2.py
cell_machine_levels/V3.py
cell_machine_levels/__init__.py
cell_machine_levels/__main__.py
cell_machine_levels/base74.py
cell_machine_levels/level.py
cell_machine_levels-0.7.1.dist-info/METADATA
cell_machine_levels-0.7.1.dist-info/WHEEL
cell_machine_levels-0.7.1.dist-info/entry_points.txt
cell_machine_levels-0.7.1.dist-info/top_level.txt
cell_machine_levels-0.7.1.dist-info/RECORD
