Metadata-Version: 2.1
Name: cell-machine-levels
Version: 0.7.1
Summary: A library for manipulating modded cell machine level codes.
Home-page: https://github.com/BlockOG/cell_machine_levels
Author: BlockOG
Author-email: blockofgamingreal@gmail.com
Project-URL: Bug Tracker, https://github.com/BlockOG/cell_machine_levels/issues
Classifier: Programming Language :: Python
Classifier: Programming Language :: Python :: 3
Classifier: License :: OSI Approved :: MIT License
Classifier: Operating System :: OS Independent
Requires-Python: >=3.6
Requires-Dist: BlockOL (>=1.3.2)
